raidium/__init__.py
raidium/raidium.py
raidium-1.0.8.dist-info/LICENSE
raidium-1.0.8.dist-info/METADATA
raidium-1.0.8.dist-info/WHEEL
raidium-1.0.8.dist-info/top_level.txt
raidium-1.0.8.dist-info/RECORD
