Metadata-Version: 2.1
Name: raidium
Version: 1.0.8
Summary: Module for Cheat Listening in your Album on the VKontakte Social Network.
Home-page: https://github.com/mrshowtv/vk-listener
Author: k3rry1xrd
Author-email: Mrslashkaopenko@google.com
License: UNKNOWN
Project-URL: Bug Tracker, https://github.com/mrshowtv/vk-listener
Platform: UNKNOWN
Classifier: Programming Language :: Python :: 3
Classifier: License :: OSI Approved :: MIT License
Classifier: Operating System :: OS Independent
Requires-Python: >=3.0
